SCRY-1.2.5.dist-info/DESCRIPTION.rst
SCRY-1.2.5.dist-info/METADATA
SCRY-1.2.5.dist-info/RECORD
SCRY-1.2.5.dist-info/WHEEL
SCRY-1.2.5.dist-info/entry_points.txt
SCRY-1.2.5.dist-info/metadata.json
SCRY-1.2.5.dist-info/top_level.txt
scry/__init__.py
scry/cmd.py
scry/config.py
scry/utility.py
scry/app/__init__.py
scry/app/log.py
scry/app/query_wrapper.py
scry/app/routes.py
scry/query/__init__.py
scry/query/contexts.py
scry/query/core.py
scry/query/patch.py
scry/resources/config.default
scry/resources/css/query.css
scry/resources/css/sidebar.css
scry/resources/css/styles.css
scry/resources/css/yasgui.min.css
scry/resources/html/about.html
scry/resources/html/contact.html
scry/resources/html/error.html
scry/resources/html/query.html
scry/resources/html/services.html
scry/resources/html/sidebar.html
scry/resources/html/template.html
scry/resources/html/update.html
scry/resources/img/background.jpg
scry/resources/img/box-bottom.png
scry/resources/img/box-top.png
scry/resources/img/header-left.png
scry/resources/img/header-right.png
scry/resources/img/home.png
scry/resources/img/location.png
scry/resources/img/mail.png
scry/resources/img/phone.png
scry/resources/img/python.png
scry/resources/js/jquery.min.js
scry/resources/js/jsapi.js
scry/resources/js/yasgui.min.js
scry/resources/sparql/demo1.sparql
scry/services/__init__.py
scry/services/classes.py
