Metadata-Version: 2.0
Name: SCRY
Version: 1.2.5
Summary: SPARQL Compatible seRvice laYer
Home-page: http://www.few.vu.nl/
Author: Bas Stringer
Author-email: b.stringer@vu.nl
License: MIT
Keywords: scry sparql rdf linked open data service services custom customized extension
Platform: UNKNOWN
Classifier: Development Status :: 4 - Beta
Classifier: Environment :: Web Environment
Classifier: Intended Audience :: Developers
Classifier: Intended Audience :: Information Technology
Classifier: Intended Audience :: Science/Research
Classifier: License :: OSI Approved :: MIT License
Classifier: Operating System :: OS Independent
Classifier: Programming Language :: Python :: 2
Classifier: Programming Language :: Python :: 2.7
Classifier: Topic :: Internet :: WWW/HTTP :: WSGI
Classifier: Topic :: Scientific/Engineering
Classifier: Topic :: Software Development
Requires-Dist: flask (>=0.10.1)
Requires-Dist: pip (>=8.0.0)
Requires-Dist: rdflib (>=4.2.1)
Requires-Dist: sparqlwrapper (>=1.7.6)
